randsymbols/__init__.py
randsymbols/__main__.py
randsymbols/alphabets/__init__.py
randsymbols/alphabets/alphanumeric.py
randsymbols/alphabets/anyprintable.py
randsymbols/alphabets/emoji.py
randsymbols-1.0.0.dist-info/LICENSE
randsymbols-1.0.0.dist-info/METADATA
randsymbols-1.0.0.dist-info/WHEEL
randsymbols-1.0.0.dist-info/entry_points.txt
randsymbols-1.0.0.dist-info/top_level.txt
randsymbols-1.0.0.dist-info/RECORD
