Metadata-Version: 2.1
Name: randsymbols
Version: 1.0.0
Summary: Generate random symbols
Author: trurlem
License: The MIT License (MIT)
Project-URL: Homepage, https://github.com/trurlem/randsymbols
Keywords: random,cli
Classifier: License :: OSI Approved :: MIT License
Classifier: Programming Language :: Python
Classifier: Programming Language :: Python :: 3
Requires-Python: >=3.9
License-File: LICENSE
Requires-Dist: typer[all] (>=0.4)
Requires-Dist: emojis (>=0.6)
Provides-Extra: build
Requires-Dist: build ; extra == 'build'
Requires-Dist: twine ; extra == 'build'
Provides-Extra: dev
Requires-Dist: black ; extra == 'dev'
Requires-Dist: bumpver ; extra == 'dev'
Requires-Dist: isort ; extra == 'dev'
